nnext/__init__.py
nnext/conversions/__init__.py
nnext/conversions/common_types.py
nnext/conversions/conversion.py
nnext/grpc/__init__.py
nnext/grpc/collections.proto
nnext/grpc/collections_service.proto
nnext/grpc/json_with_int.proto
nnext/grpc/nnext.proto
nnext/grpc/points.proto
nnext/grpc/points_service.proto
nnext/grpc/snapshots_service.proto
nnext/http/__init__.py
nnext/http/api/__init__.py
nnext/http/api/cluster_api.py
nnext/http/api/collections_api.py
nnext/http/api/default_api.py
nnext/http/api/points_api.py
nnext/http/api/snapshots_api.py
nnext/http/api_client.py
nnext/http/configuration.py
nnext/http/exceptions.py
nnext/http/models/__init__.py
nnext/http/models/models.py
nnext/nnext_client.py
nnext/parallel_processor.py
nnext/uploader/__init__.py
nnext/uploader/grpc_uploader.py
nnext/uploader/rest_uploader.py
nnext/uploader/uploader.py
nnext-0.0.43.dist-info/WHEEL
nnext-0.0.43.dist-info/METADATA
nnext-0.0.43.dist-info/RECORD
