Metadata-Version: 2.1
Name: nnext
Version: 0.0.43
Summary: Client library for the NNext Neural search engine
Home-page: https://nnext.io/docs/Python-22a9be22c5cf4869bda849e3f06c0993
Keywords: neural search,semantic,search,engine,client
Author: NNext Team
Author-email: team@nnext.ai
Requires-Python: >=3.7,<4.0
Classifier: Programming Language :: Python :: 3
Classifier: Programming Language :: Python :: 3.7
Classifier: Programming Language :: Python :: 3.8
Classifier: Programming Language :: Python :: 3.9
Classifier: Programming Language :: Python :: 3.10
Classifier: Programming Language :: Python :: 3.11
Requires-Dist: betterproto (==2.0.0b4)
Requires-Dist: grpcio (>=1.46.0,<2.0.0)
Requires-Dist: httpx[http2] (>=0.23.0,<0.24.0)
Requires-Dist: loguru (>=0.5.3,<0.6.0)
Requires-Dist: nest-asyncio (>=1.5.5,<2.0.0)
Requires-Dist: numpy (>=1.21,<2.0)
Requires-Dist: pydantic (>=1.8,<2.0)
Requires-Dist: tqdm (>=4.56.0,<5.0.0)
Requires-Dist: typing-extensions (>=4.0.0,<5.0.0)
Project-URL: Repository, https://github.com/nnextai/pynnext
